HGQ/__init__.py
HGQ/_patch.py
HGQ/_version.py
HGQ/bops/__init__.py
HGQ/bops/bops.py
HGQ/layers/__init__.py
HGQ/layers/base.py
HGQ/layers/batchnorm_base.py
HGQ/layers/conv.py
HGQ/layers/dense.py
HGQ/layers/misc.py
HGQ/layers/passive_layers.py
HGQ/layers/experimental/__init__.py
HGQ/layers/experimental/attn.py
HGQ/proxy/__init__.py
HGQ/proxy/convert.py
HGQ/proxy/fixed_point_quantizer.py
HGQ/proxy/precision_derivation.py
HGQ/proxy/unary_lut.py
HGQ/proxy/plugins/__init__.py
HGQ/proxy/plugins/qkeras.py
HGQ/quantizer/__init__.py
HGQ/quantizer/quantizer.py
HGQ/utils/__init__.py
HGQ/utils/utils.py
hgq-0.2.6.dist-info/licenses/LICENSE
hgq-0.2.6.dist-info/METADATA
hgq-0.2.6.dist-info/WHEEL
hgq-0.2.6.dist-info/top_level.txt
hgq-0.2.6.dist-info/RECORD
