Metadata-Version: 2.4
Name: HGQ
Version: 0.2.6
Summary: High Granularity Quantizarion
Author-email: Chang Sun <chsun@cern.ch>
License:                                  Apache License
Project-URL: repository, https://github.com/calad0i/HGQ
Classifier: Programming Language :: Python :: 3
Classifier: Operating System :: OS Independent
Classifier: License :: OSI Approved :: Apache Software License
Classifier: Development Status :: 5 - Production/Stable
Requires-Python: >=3.10
License-File: LICENSE
Requires-Dist: tensorflow>=2.13
Requires-Dist: numpy>=1.23
Requires-Dist: keras<3
Provides-Extra: docs
Requires-Dist: sphinx; extra == "docs"
Requires-Dist: sphinx-rtd-theme; extra == "docs"
Requires-Dist: myst-parser; extra == "docs"
Requires-Dist: qkeras; extra == "docs"
Requires-Dist: pyparsing; extra == "docs"
Provides-Extra: test
Requires-Dist: hls4ml>=1.0; extra == "test"
Requires-Dist: qkeras; extra == "test"
Requires-Dist: pytest; extra == "test"
Requires-Dist: pytest-xdist; extra == "test"
Requires-Dist: pytest-env; extra == "test"
Requires-Dist: pytest-cov; extra == "test"
Requires-Dist: pytest-sugar; extra == "test"
Requires-Dist: pyparsing; extra == "test"
Dynamic: license-file
